{
  "domain": "clinicaltrials.gov",
  "url_pattern": "/*",
  "title": "ClinicalTrials.gov Registry",
  "description": "Search and extract clinical trial data including safety endpoints, SAEs, and study design",
  "tools": [
    {
      "name": "search-trials",
      "description": "Search clinical trials by drug, condition, sponsor, or status",
      "parameters": [
        {"name": "query", "type": "string", "description": "Free-text search query", "required": true},
        {"name": "condition", "type": "string", "description": "Medical condition or disease", "required": false},
        {"name": "intervention", "type": "string", "description": "Drug or intervention name", "required": false},
        {"name": "status", "type": "string", "description": "Trial status (recruiting, completed, terminated)", "required": false},
        {"name": "phase", "type": "string", "description": "Trial phase (1, 2, 3, 4)", "required": false},
        {"name": "limit", "type": "integer", "description": "Maximum results to return", "required": false}
      ],
      "stub_response": "{\"status\": \"stub\", \"message\": \"Will query ClinicalTrials.gov API v2 with structured field mapping.\"}"
    },
    {
      "name": "get-trial",
      "description": "Get full trial record by NCT ID",
      "parameters": [
        {"name": "nct_id", "type": "string", "description": "NCT identifier (e.g., NCT04280705)", "required": true}
      ],
      "stub_response": "{\"status\": \"stub\", \"message\": \"Will fetch study record via ClinicalTrials.gov API v2 /studies/{nctId}.\"}"
    },
    {
      "name": "get-safety-endpoints",
      "description": "Extract safety and adverse event endpoints from a trial",
      "parameters": [
        {"name": "nct_id", "type": "string", "description": "NCT identifier", "required": true}
      ],
      "stub_response": "{\"status\": \"stub\", \"message\": \"Will parse outcomesModule for safety-related primary and secondary endpoints.\"}"
    },
    {
      "name": "get-serious-adverse-events",
      "description": "Get reported serious adverse events from trial results",
      "parameters": [
        {"name": "nct_id", "type": "string", "description": "NCT identifier", "required": true}
      ],
      "stub_response": "{\"status\": \"stub\", \"message\": \"Will extract SAE table from resultsSection.adverseEventsModule.\"}"
    },
    {
      "name": "compare-trial-arms",
      "description": "Compare adverse event rates between treatment and control arms",
      "parameters": [
        {"name": "nct_id", "type": "string", "description": "NCT identifier", "required": true}
      ]
    }
  ]
}
