{
  "domain": "cloud.nexvigilant.com",
  "url_pattern": "/*",
  "title": "Cloud Infrastructure",
  "description": "Anomaly detection, autoscaling, deployment, monitoring, and cost optimization",
  "tools": [
    {
      "name": "cloud-anomaly-detect",
      "description": "cloud_anomaly_detect \u2014 Type + observed \u2192 drift detection.",
      "parameters": [],
      "outputSchema": {
        "type": "object",
        "properties": {
          "status": {
            "type": "string",
            "description": "ok | error"
          }
        },
        "required": [
          "status"
        ]
      },
      "annotations": {
        "readOnlyHint": true,
        "destructiveHint": false
      }
    },
    {
      "name": "cloud-architecture-advisor",
      "description": "cloud_architecture_advisor \u2014 Primitives + constraints \u2192 ranked recommendations.",
      "parameters": [],
      "outputSchema": {
        "type": "object",
        "properties": {
          "status": {
            "type": "string",
            "description": "ok | error"
          }
        },
        "required": [
          "status"
        ]
      },
      "annotations": {
        "readOnlyHint": true,
        "destructiveHint": false
      }
    },
    {
      "name": "cloud-capacity-project",
      "description": "cloud_capacity_project \u2014 Pure computation: utilization projection over time.",
      "parameters": [],
      "outputSchema": {
        "type": "object",
        "properties": {
          "status": {
            "type": "string",
            "description": "ok | error"
          }
        },
        "required": [
          "status"
        ]
      },
      "annotations": {
        "readOnlyHint": true,
        "destructiveHint": false
      }
    },
    {
      "name": "cloud-compare-types",
      "description": "cloud_compare_types \u2014 Two types \u2192 overlap, unique-to-each, Jaccard.",
      "parameters": [],
      "outputSchema": {
        "type": "object",
        "properties": {
          "status": {
            "type": "string",
            "description": "ok | error"
          }
        },
        "required": [
          "status"
        ]
      },
      "annotations": {
        "readOnlyHint": true,
        "destructiveHint": false
      }
    },
    {
      "name": "cloud-dominant-shift",
      "description": "character.",
      "parameters": [],
      "outputSchema": {
        "type": "object",
        "properties": {
          "status": {
            "type": "string",
            "description": "ok | error"
          }
        },
        "required": [
          "status"
        ]
      },
      "annotations": {
        "readOnlyHint": true,
        "destructiveHint": false
      }
    },
    {
      "name": "cloud-infra-map",
      "description": "cloud_infra_map \u2014 Single instance \u2192 full model with composition overlay.",
      "parameters": [],
      "outputSchema": {
        "type": "object",
        "properties": {
          "status": {
            "type": "string",
            "description": "ok | error"
          }
        },
        "required": [
          "status"
        ]
      },
      "annotations": {
        "readOnlyHint": true,
        "destructiveHint": false
      }
    },
    {
      "name": "cloud-infra-status",
      "description": "cloud_infra_status \u2014 GCE instance list mapped through cloud primitives.",
      "parameters": [],
      "outputSchema": {
        "type": "object",
        "properties": {
          "status": {
            "type": "string",
            "description": "ok | error"
          }
        },
        "required": [
          "status"
        ]
      },
      "annotations": {
        "readOnlyHint": true,
        "destructiveHint": false
      }
    },
    {
      "name": "cloud-list-types",
      "description": "cloud_list_types \u2014 Inventory of all 35 types, filterable by tier.",
      "parameters": [],
      "outputSchema": {
        "type": "object",
        "properties": {
          "status": {
            "type": "string",
            "description": "ok | error"
          }
        },
        "required": [
          "status"
        ]
      },
      "annotations": {
        "readOnlyHint": true,
        "destructiveHint": false
      }
    },
    {
      "name": "cloud-molecular-weight",
      "description": "dedicated molecular_weight tool group.",
      "parameters": [],
      "outputSchema": {
        "type": "object",
        "properties": {
          "status": {
            "type": "string",
            "description": "ok | error"
          }
        },
        "required": [
          "status"
        ]
      },
      "annotations": {
        "readOnlyHint": true,
        "destructiveHint": false
      }
    },
    {
      "name": "cloud-primitive-composition",
      "description": "cloud_primitive_composition \u2014 Type name \u2192 full primitive composition + transfers.",
      "parameters": [],
      "outputSchema": {
        "type": "object",
        "properties": {
          "status": {
            "type": "string",
            "description": "ok | error"
          }
        },
        "required": [
          "status"
        ]
      },
      "annotations": {
        "readOnlyHint": true,
        "destructiveHint": false
      }
    },
    {
      "name": "cloud-reverse-synthesize",
      "description": "cloud_reverse_synthesize \u2014 Primitives \u2192 ranked cloud type matches.",
      "parameters": [],
      "outputSchema": {
        "type": "object",
        "properties": {
          "status": {
            "type": "string",
            "description": "ok | error"
          }
        },
        "required": [
          "status"
        ]
      },
      "annotations": {
        "readOnlyHint": true,
        "destructiveHint": false
      }
    },
    {
      "name": "cloud-reverse-transfer",
      "description": "cloud_reverse_transfer \u2014 Domain concept \u2192 matching cloud types.",
      "parameters": [],
      "outputSchema": {
        "type": "object",
        "properties": {
          "status": {
            "type": "string",
            "description": "ok | error"
          }
        },
        "required": [
          "status"
        ]
      },
      "annotations": {
        "readOnlyHint": true,
        "destructiveHint": false
      }
    },
    {
      "name": "cloud-supervisor-health",
      "description": "cloud_supervisor_health \u2014 Nexcloud supervisor status through cloud primitives.",
      "parameters": [],
      "outputSchema": {
        "type": "object",
        "properties": {
          "status": {
            "type": "string",
            "description": "ok | error"
          }
        },
        "required": [
          "status"
        ]
      },
      "annotations": {
        "readOnlyHint": true,
        "destructiveHint": false
      }
    },
    {
      "name": "cloud-tier-classify",
      "description": "cloud_tier_classify \u2014 Primitive names \u2192 tier classification.",
      "parameters": [],
      "outputSchema": {
        "type": "object",
        "properties": {
          "status": {
            "type": "string",
            "description": "ok | error"
          }
        },
        "required": [
          "status"
        ]
      },
      "annotations": {
        "readOnlyHint": true,
        "destructiveHint": false
      }
    },
    {
      "name": "cloud-transfer-chain",
      "description": "cloud_transfer_chain \u2014 Multi-hop BFS across transfer graph.",
      "parameters": [],
      "outputSchema": {
        "type": "object",
        "properties": {
          "status": {
            "type": "string",
            "description": "ok | error"
          }
        },
        "required": [
          "status"
        ]
      },
      "annotations": {
        "readOnlyHint": true,
        "destructiveHint": false
      }
    },
    {
      "name": "cloud-transfer-confidence",
      "description": "Compute cross-domain transfer confidence from structural, functional, and contextual similarity.",
      "parameters": [],
      "outputSchema": {
        "type": "object",
        "properties": {
          "status": {
            "type": "string",
            "description": "ok | error"
          }
        },
        "required": [
          "status"
        ]
      },
      "annotations": {
        "readOnlyHint": true,
        "destructiveHint": false
      }
    },
    {
      "name": "cloud-transfer-matrix",
      "description": "cloud_transfer_matrix \u2014 Full type\u00d7domain confidence matrix.",
      "parameters": [],
      "outputSchema": {
        "type": "object",
        "properties": {
          "status": {
            "type": "string",
            "description": "ok | error"
          }
        },
        "required": [
          "status"
        ]
      },
      "annotations": {
        "readOnlyHint": true,
        "destructiveHint": false
      }
    }
  ],
  "proxy": "rust-native"
}
