{
  "domain": "frontier.nexvigilant.com",
  "url_pattern": "/*",
  "title": "Exploration Frontier",
  "description": "Mission launch, discovery recording, and frontier tracking",
  "tools": [
    {
      "name": "explore-get-frontier",
      "description": "- Coverage percentage",
      "parameters": [],
      "outputSchema": {
        "type": "object",
        "properties": {
          "status": {
            "type": "string",
            "description": "ok | error"
          }
        },
        "required": [
          "status"
        ]
      },
      "annotations": {
        "readOnlyHint": true,
        "destructiveHint": false
      }
    },
    {
      "name": "explore-launch-mission",
      "description": "- Success probability",
      "parameters": [],
      "outputSchema": {
        "type": "object",
        "properties": {
          "status": {
            "type": "string",
            "description": "ok | error"
          }
        },
        "required": [
          "status"
        ]
      },
      "annotations": {
        "readOnlyHint": true,
        "destructiveHint": false
      }
    },
    {
      "name": "explore-record-discovery",
      "description": "- Whether it's significant (>0.7)",
      "parameters": [],
      "outputSchema": {
        "type": "object",
        "properties": {
          "status": {
            "type": "string",
            "description": "ok | error"
          }
        },
        "required": [
          "status"
        ]
      },
      "annotations": {
        "readOnlyHint": true,
        "destructiveHint": false
      }
    }
  ],
  "proxy": "rust-native"
}
