{
  "domain": "www.pmda.go.jp",
  "url_pattern": "/*",
  "title": "PMDA Japan Pharmaceuticals",
  "description": "Japanese Pharmaceuticals and Medical Devices Agency \u2014 adverse drug reaction reports, safety information, and drug approvals",
  "tools": [
    {
      "name": "search-safety-information",
      "description": "Search PMDA safety communications and Dear Healthcare Professional letters",
      "parameters": [
        {
          "name": "drug_name",
          "type": "string",
          "description": "Drug name (brand or generic)",
          "required": true
        }
      ],
      "outputSchema": {
        "type": "object",
        "properties": {
          "status": {
            "type": "string",
            "description": "ok | error | stub"
          },
          "count": {
            "type": "integer"
          },
          "results": {
            "type": "array",
            "items": {
              "type": "object"
            }
          }
        },
        "required": [
          "status",
          "results"
        ]
      },
      "annotations": {
        "readOnlyHint": true,
        "destructiveHint": false
      }
    },
    {
      "name": "get-adverse-reactions",
      "description": "Search Japanese adverse drug reaction case reports",
      "parameters": [
        {
          "name": "drug_name",
          "type": "string",
          "description": "Drug name (brand or generic)",
          "required": true
        },
        {
          "name": "limit",
          "type": "int",
          "description": "Maximum results to return",
          "required": false,
          "default": "25"
        }
      ],
      "outputSchema": {
        "type": "object",
        "properties": {
          "status": {
            "type": "string",
            "description": "ok | error | stub"
          },
          "data": {
            "type": "object"
          }
        },
        "required": [
          "status"
        ]
      },
      "annotations": {
        "readOnlyHint": true,
        "destructiveHint": false
      }
    },
    {
      "name": "get-drug-approval",
      "description": "Get Japanese drug approval information including review reports",
      "parameters": [
        {
          "name": "drug_name",
          "type": "string",
          "description": "Drug name (brand or generic)",
          "required": true
        }
      ],
      "outputSchema": {
        "type": "object",
        "properties": {
          "status": {
            "type": "string",
            "description": "ok | error | stub"
          },
          "data": {
            "type": "object"
          }
        },
        "required": [
          "status"
        ]
      },
      "annotations": {
        "readOnlyHint": true,
        "destructiveHint": false
      }
    },
    {
      "name": "get-rmp-summary",
      "description": "Get Risk Management Plan summary for a Japanese-approved drug",
      "parameters": [
        {
          "name": "drug_name",
          "type": "string",
          "description": "Drug name (brand or generic)",
          "required": true
        }
      ],
      "outputSchema": {
        "type": "object",
        "properties": {
          "status": {
            "type": "string",
            "description": "ok | error | stub"
          },
          "data": {
            "type": "object"
          }
        },
        "required": [
          "status"
        ]
      },
      "annotations": {
        "readOnlyHint": true,
        "destructiveHint": false
      }
    },
    {
      "name": "get-reevaluation-results",
      "description": "Get post-marketing re-evaluation results",
      "parameters": [
        {
          "name": "drug_name",
          "type": "string",
          "description": "Drug name (brand or generic)",
          "required": true
        }
      ],
      "outputSchema": {
        "type": "object",
        "properties": {
          "status": {
            "type": "string",
            "description": "ok | error | stub"
          },
          "data": {
            "type": "object"
          }
        },
        "required": [
          "status"
        ]
      },
      "annotations": {
        "readOnlyHint": true,
        "destructiveHint": false
      }
    },
    {
      "name": "search-relief-cases",
      "description": "Search PMDA adverse drug reaction relief system cases",
      "parameters": [
        {
          "name": "drug_name",
          "type": "string",
          "description": "Drug name (brand or generic)",
          "required": true
        }
      ],
      "outputSchema": {
        "type": "object",
        "properties": {
          "status": {
            "type": "string",
            "description": "ok | error | stub"
          },
          "count": {
            "type": "integer"
          },
          "results": {
            "type": "array",
            "items": {
              "type": "object"
            }
          }
        },
        "required": [
          "status",
          "results"
        ]
      },
      "annotations": {
        "readOnlyHint": true,
        "destructiveHint": false
      }
    }
  ],
  "proxy": "scripts/www_pmda_go_jp_proxy.py"
}
